parsanlp/__init__.py
parsanlp/helper_functions.py
parsanlp/transformers.py
parsanlp-1.2.0.dist-info/METADATA
parsanlp-1.2.0.dist-info/WHEEL
parsanlp-1.2.0.dist-info/licenses/LICENSE
parsanlp-1.2.0.dist-info/RECORD
