Metadata-Version: 2.1
Name: parsanlp
Version: 1.2.0
Summary: A package to help with NLP tasks
Author: Parsa Hemmati
License-File: LICENSE
Classifier: License :: OSI Approved :: MIT License
Classifier: Operating System :: OS Independent
Classifier: Programming Language :: Python :: 3
Requires-Python: >=3.7
